{
  "date": "2026-05-23",
  "generated_at": "2026-07-05T14:24:26.227Z",
  "schema": "games_v1",
  "formula_version": "v2",
  "games": [
    {
      "game_pk": 824518,
      "matchup": "STL @ CIN",
      "home": "CIN",
      "away": "STL",
      "status": "Final",
      "model_p": 0.527,
      "signal": 0.3142,
      "adrian_p": 0.677,
      "agree": 4,
      "ml_pick": "CIN",
      "factor_leans": {
        "momentum": 0.1455,
        "pitching": -0.2912,
        "f5": -0.0835,
        "bats": 1.1641,
        "schedule": 0.1267,
        "manager": 0.1515
      },
      "news_delta": 0.16,
      "base": 10.43,
      "adj_total": 11.3824,
      "line": 10.5,
      "side": "over",
      "p_over": 0.62,
      "components": {
        "aStart": 0.0836,
        "hStart": 0.9438,
        "homeContact": -0.042,
        "awayContact": -0.033,
        "aFat": 0,
        "hFat": 0
      },
      "streak_home": 2,
      "streak_away": -2,
      "pitcher_recent": {
        "home": {
          "era": 8.49,
          "n": 3,
          "fatigue": "normal"
        },
        "away": {
          "era": 4.58,
          "n": 3,
          "fatigue": "normal"
        }
      },
      "formula_version": "v2",
      "graded": true,
      "date": "2026-05-23",
      "game_date": "2026-05-23",
      "park_factor": 1.088,
      "elo_diff": 3.1000000000001364,
      "sp_fip_diff": 0.258,
      "home_win": 0,
      "total_runs": 9,
      "final": "8-1",
      "ml_result": "loss",
      "total_result": "loss",
      "backfilled": true
    },
    {
      "game_pk": 824516,
      "matchup": "STL @ CIN",
      "home": "CIN",
      "away": "STL",
      "status": "Final",
      "model_p": 0.512,
      "signal": -0.004,
      "adrian_p": 0.509,
      "agree": 4,
      "ml_pick": "CIN",
      "factor_leans": {
        "momentum": 0.1455,
        "pitching": -1.308,
        "f5": -0.5475,
        "bats": 1.1641,
        "schedule": 0.1267,
        "manager": 0.1515
      },
      "news_delta": 0.16,
      "base": 9.69,
      "adj_total": 9.0562,
      "line": 9.5,
      "side": "under",
      "p_over": 0.439,
      "components": {
        "aStart": -0.682,
        "hStart": 0.1232,
        "homeContact": -0.042,
        "awayContact": -0.033,
        "aFat": 0,
        "hFat": 0
      },
      "streak_home": 2,
      "streak_away": -2,
      "pitcher_recent": {
        "home": {
          "era": 4.76,
          "n": 1,
          "fatigue": "normal"
        },
        "away": {
          "era": 1.1,
          "n": 3,
          "fatigue": "normal"
        }
      },
      "formula_version": "v2",
      "graded": true,
      "date": "2026-05-23",
      "game_date": "2026-05-23",
      "park_factor": 1.088,
      "elo_diff": 3.1000000000001364,
      "sp_fip_diff": 1.5290000000000004,
      "home_win": 1,
      "total_runs": 13,
      "final": "6-7",
      "ml_result": "win",
      "total_result": "loss",
      "backfilled": true
    },
    {
      "game_pk": 824674,
      "matchup": "HOU @ CHC",
      "home": "CHC",
      "away": "HOU",
      "status": "Final",
      "model_p": 0.557,
      "signal": -0.2144,
      "adrian_p": 0.407,
      "agree": 2,
      "ml_pick": "HOU",
      "factor_leans": {
        "momentum": -0.8,
        "pitching": -0.164,
        "f5": 0.015,
        "bats": 0.4053,
        "schedule": 0.1711,
        "manager": 0
      },
      "news_delta": -0.08,
      "base": 8.37,
      "adj_total": 8.5396,
      "line": 8.5,
      "side": "over",
      "p_over": 0.505,
      "components": {
        "aStart": -0.33,
        "hStart": 0.4576,
        "homeContact": 0.03,
        "awayContact": 0.012,
        "aFat": 0,
        "hFat": 0
      },
      "streak_home": -6,
      "streak_away": 1,
      "pitcher_recent": {
        "home": {
          "era": 6.28,
          "n": 3,
          "fatigue": "normal"
        },
        "away": {
          "era": 2.7,
          "n": 3,
          "fatigue": "normal"
        }
      },
      "formula_version": "v2",
      "graded": true,
      "date": "2026-05-23",
      "game_date": "2026-05-23",
      "park_factor": 0.963,
      "elo_diff": 26.5,
      "sp_fip_diff": 0.09700000000000042,
      "home_win": 0,
      "total_runs": 3,
      "final": "3-0",
      "ml_result": "win",
      "total_result": "loss",
      "backfilled": true
    },
    {
      "game_pk": 822814,
      "matchup": "PIT @ TOR",
      "home": "TOR",
      "away": "PIT",
      "status": "Final",
      "model_p": 0.535,
      "signal": -0.5045,
      "adrian_p": 0.385,
      "agree": 4,
      "ml_pick": "PIT",
      "factor_leans": {
        "momentum": 0.6182,
        "pitching": -1.2963,
        "f5": -0.515,
        "bats": -0.5724,
        "schedule": 0.0133,
        "manager": -0.1087
      },
      "news_delta": -0.15,
      "base": 7.99,
      "adj_total": 7.6432,
      "line": 8,
      "side": "under",
      "p_over": 0.451,
      "components": {
        "aStart": -0.4532,
        "hStart": 0.2354,
        "homeContact": -0.135,
        "awayContact": 0.006,
        "aFat": 0,
        "hFat": 0
      },
      "streak_home": 3,
      "streak_away": -1,
      "pitcher_recent": {
        "home": {
          "era": 5.27,
          "n": 3,
          "fatigue": "normal"
        },
        "away": {
          "era": 2.14,
          "n": 3,
          "fatigue": "normal"
        }
      },
      "formula_version": "v2",
      "graded": true,
      "date": "2026-05-23",
      "game_date": "2026-05-23",
      "park_factor": 1.005,
      "elo_diff": 24.100000000000136,
      "sp_fip_diff": 1.487,
      "home_win": 1,
      "total_runs": 7,
      "final": "2-5",
      "ml_result": "loss",
      "total_result": "win",
      "backfilled": true
    },
    {
      "game_pk": 823458,
      "matchup": "CLE @ PHI",
      "home": "PHI",
      "away": "CLE",
      "status": "Final",
      "model_p": 0.534,
      "signal": 0.009,
      "adrian_p": 0.543,
      "agree": 3,
      "ml_pick": "PHI",
      "factor_leans": {
        "momentum": -0.9455,
        "pitching": 0.7496,
        "f5": 0.3985,
        "bats": -0.5637,
        "schedule": 0.1444,
        "manager": -0.3
      },
      "news_delta": 0.07,
      "base": 8.54,
      "adj_total": 7.385,
      "line": 8.5,
      "side": "under",
      "p_over": 0.35,
      "components": {
        "aStart": -0.4488,
        "hStart": -0.5412,
        "homeContact": -0.099,
        "awayContact": -0.066,
        "aFat": 0,
        "hFat": 0
      },
      "streak_home": -3,
      "streak_away": 7,
      "pitcher_recent": {
        "home": {
          "era": 1.74,
          "n": 3,
          "fatigue": "normal"
        },
        "away": {
          "era": 2.16,
          "n": 3,
          "fatigue": "normal"
        }
      },
      "formula_version": "v2",
      "graded": true,
      "date": "2026-05-23",
      "game_date": "2026-05-23",
      "park_factor": 1.017,
      "elo_diff": -4.100000000000136,
      "sp_fip_diff": -1.2189999999999999,
      "home_win": 1,
      "total_runs": 3,
      "final": "0-3",
      "ml_result": "win",
      "total_result": "win",
      "backfilled": true
    },
    {
      "game_pk": 823222,
      "matchup": "CWS @ SF",
      "home": "SF",
      "away": "CWS",
      "status": "Final",
      "model_p": 0.56,
      "signal": -0.1979,
      "adrian_p": 0.41,
      "agree": 3,
      "ml_pick": "CWS",
      "factor_leans": {
        "momentum": -0.8364,
        "pitching": 0.6123,
        "f5": 0.143,
        "bats": -1.1783,
        "schedule": 0.18,
        "manager": -0.1592
      },
      "news_delta": 0,
      "base": 8.23,
      "adj_total": 6.6808,
      "line": 8,
      "side": "under",
      "p_over": 0.325,
      "components": {
        "aStart": -0.924,
        "hStart": -0.4752,
        "homeContact": -0.162,
        "awayContact": 0.012,
        "aFat": 0,
        "hFat": 0
      },
      "streak_home": -4,
      "streak_away": 1,
      "pitcher_recent": {
        "home": {
          "era": 2.04,
          "n": 3,
          "fatigue": "normal"
        },
        "away": {
          "era": 0,
          "n": 2,
          "fatigue": "normal"
        }
      },
      "formula_version": "v2",
      "graded": true,
      "date": "2026-05-23",
      "game_date": "2026-05-23",
      "park_factor": 0.922,
      "elo_diff": 21,
      "sp_fip_diff": -0.5219999999999998,
      "home_win": 1,
      "total_runs": 13,
      "final": "3-10",
      "ml_result": "loss",
      "total_result": "loss",
      "backfilled": true
    },
    {
      "game_pk": 824109,
      "matchup": "SEA @ KC",
      "home": "KC",
      "away": "SEA",
      "status": "Final",
      "model_p": 0.481,
      "signal": -0.567,
      "adrian_p": 0.331,
      "agree": 5,
      "ml_pick": "SEA",
      "factor_leans": {
        "momentum": -0.8727,
        "pitching": -0.3269,
        "f5": -0.167,
        "bats": -0.7456,
        "schedule": 0.3,
        "manager": -0.2418
      },
      "news_delta": -0.16,
      "base": 8.77,
      "adj_total": 8.6824,
      "line": 9,
      "side": "under",
      "p_over": 0.456,
      "components": {
        "aStart": 0.0836,
        "hStart": 0.0088,
        "homeContact": -0.093,
        "awayContact": -0.087,
        "aFat": 0,
        "hFat": 0
      },
      "streak_home": -4,
      "streak_away": 2,
      "pitcher_recent": {
        "home": {
          "era": 4.24,
          "n": 3,
          "fatigue": "normal"
        },
        "away": {
          "era": 4.58,
          "n": 3,
          "fatigue": "normal"
        }
      },
      "formula_version": "v2",
      "graded": true,
      "date": "2026-05-23",
      "game_date": "2026-05-23",
      "park_factor": 1.06,
      "elo_diff": -34.5,
      "sp_fip_diff": 0.33199999999999985,
      "home_win": 1,
      "total_runs": 5,
      "final": "0-5",
      "ml_result": "loss",
      "total_result": "win",
      "backfilled": true
    },
    {
      "game_pk": 824760,
      "matchup": "MIN @ BOS",
      "home": "BOS",
      "away": "MIN",
      "status": "Final",
      "model_p": 0.575,
      "signal": 0.3433,
      "adrian_p": 0.725,
      "agree": 3,
      "ml_pick": "BOS",
      "factor_leans": {
        "momentum": -0.1818,
        "pitching": 0.6328,
        "f5": 0.104,
        "bats": -0.6455,
        "schedule": 0.3,
        "manager": -0.0985
      },
      "news_delta": 0.3,
      "base": 9.75,
      "adj_total": 10.6204,
      "line": 10,
      "side": "over",
      "p_over": 0.585,
      "components": {
        "aStart": 0.1012,
        "hStart": 0.7722,
        "homeContact": -0.123,
        "awayContact": -0.03,
        "aFat": 0.15,
        "hFat": 0
      },
      "streak_home": -1,
      "streak_away": 2,
      "pitcher_recent": {
        "home": {
          "era": 7.71,
          "n": 3,
          "fatigue": "normal"
        },
        "away": {
          "era": 4.66,
          "n": 3,
          "fatigue": "media"
        }
      },
      "formula_version": "v2",
      "graded": true,
      "date": "2026-05-23",
      "game_date": "2026-05-23",
      "park_factor": 1.112,
      "elo_diff": 33.700000000000045,
      "sp_fip_diff": -0.23500000000000032,
      "home_win": 0,
      "total_runs": 6,
      "final": "4-2",
      "ml_result": "loss",
      "total_result": "loss",
      "backfilled": true
    },
    {
      "game_pk": 824920,
      "matchup": "WSH @ ATL",
      "home": "ATL",
      "away": "WSH",
      "status": "Final",
      "model_p": 0.616,
      "signal": 0.0732,
      "adrian_p": 0.682,
      "agree": 4,
      "ml_pick": "ATL",
      "factor_leans": {
        "momentum": 0.7273,
        "pitching": 1.0208,
        "f5": 0.3535,
        "bats": -0.4895,
        "schedule": 0.1,
        "manager": -0.3
      },
      "news_delta": -0.3,
      "base": 10.28,
      "adj_total": 11.375,
      "line": 10.5,
      "side": "over",
      "p_over": 0.619,
      "components": {
        "aStart": 0.891,
        "hStart": 0,
        "homeContact": 0.15,
        "awayContact": 0.054,
        "aFat": 0,
        "hFat": 0
      },
      "streak_home": 4,
      "streak_away": -2,
      "pitcher_recent": {
        "home": {
          "era": 4.2,
          "n": 3,
          "fatigue": "normal"
        },
        "away": {
          "era": 8.25,
          "n": 3,
          "fatigue": "normal"
        }
      },
      "formula_version": "v2",
      "graded": true,
      "date": "2026-05-23",
      "game_date": "2026-05-23",
      "park_factor": 1.013,
      "elo_diff": 66.79999999999995,
      "sp_fip_diff": -0.9900000000000002,
      "home_win": 0,
      "total_runs": 2,
      "final": "2-0",
      "ml_result": "loss",
      "total_result": "loss",
      "backfilled": true
    },
    {
      "game_pk": 823862,
      "matchup": "NYM @ MIA",
      "home": "MIA",
      "away": "NYM",
      "status": "Final",
      "model_p": 0.506,
      "signal": -0.0819,
      "adrian_p": 0.432,
      "agree": 3,
      "ml_pick": "NYM",
      "factor_leans": {
        "momentum": -0.2182,
        "pitching": -0.7283,
        "f5": -0.2215,
        "bats": 0.0095,
        "schedule": 0.0853,
        "manager": 0.3
      },
      "news_delta": 0.15,
      "base": 8.28,
      "adj_total": 7.475,
      "line": 8.5,
      "side": "under",
      "p_over": 0.362,
      "components": {
        "aStart": -0.3058,
        "hStart": -0.2112,
        "homeContact": -0.078,
        "awayContact": -0.21,
        "aFat": 0,
        "hFat": 0
      },
      "streak_home": 1,
      "streak_away": -1,
      "pitcher_recent": {
        "home": {
          "era": 3.24,
          "n": 3,
          "fatigue": "normal"
        },
        "away": {
          "era": 2.81,
          "n": 3,
          "fatigue": "normal"
        }
      },
      "formula_version": "v2",
      "graded": true,
      "date": "2026-05-23",
      "game_date": "2026-05-23",
      "park_factor": 0.948,
      "elo_diff": -9.899999999999864,
      "sp_fip_diff": 0.5730000000000004,
      "home_win": 1,
      "total_runs": 5,
      "final": "1-4",
      "ml_result": "loss",
      "total_result": "win",
      "backfilled": true
    },
    {
      "game_pk": 823787,
      "matchup": "LAD @ MIL",
      "home": "MIL",
      "away": "LAD",
      "status": "Final",
      "model_p": 0.543,
      "signal": 0.1716,
      "adrian_p": 0.693,
      "agree": 5,
      "ml_pick": "MIL",
      "factor_leans": {
        "momentum": 0.3636,
        "pitching": 0.5427,
        "f5": 0.123,
        "bats": -0.1272,
        "schedule": 0.3,
        "manager": 0.3
      },
      "news_delta": -0.08,
      "base": 9.4,
      "adj_total": 9.402,
      "line": 9.5,
      "side": "under",
      "p_over": 0.487,
      "components": {
        "aStart": -0.154,
        "hStart": 0.066,
        "homeContact": -0.057,
        "awayContact": 0.147,
        "aFat": 0,
        "hFat": 0
      },
      "streak_home": 4,
      "streak_away": -1,
      "pitcher_recent": {
        "home": {
          "era": 4.5,
          "n": 1,
          "fatigue": "normal"
        },
        "away": {
          "era": 3.5,
          "n": 3,
          "fatigue": "normal"
        }
      },
      "formula_version": "v2",
      "graded": true,
      "date": "2026-05-23",
      "game_date": "2026-05-23",
      "park_factor": 1,
      "elo_diff": 7.900000000000091,
      "sp_fip_diff": -0.4189999999999996,
      "home_win": 0,
      "total_runs": 14,
      "final": "11-3",
      "ml_result": "loss",
      "total_result": "loss",
      "backfilled": true
    },
    {
      "game_pk": 823300,
      "matchup": "OAK @ SD",
      "home": "SD",
      "away": "OAK",
      "status": "Final",
      "model_p": 0.615,
      "signal": 0.1797,
      "adrian_p": 0.765,
      "agree": 5,
      "ml_pick": "SD",
      "factor_leans": {
        "momentum": 0.2182,
        "pitching": 0.6608,
        "f5": 0.1385,
        "bats": -0.4669,
        "schedule": 0.0956,
        "manager": 0.3
      },
      "news_delta": 0,
      "base": 8.31,
      "adj_total": 7.9146,
      "line": 8.5,
      "side": "under",
      "p_over": 0.42,
      "components": {
        "aStart": -0.6534,
        "hStart": 0.264,
        "homeContact": -0.174,
        "awayContact": 0.018,
        "aFat": 0.15,
        "hFat": 0
      },
      "streak_home": 1,
      "streak_away": -1,
      "pitcher_recent": {
        "home": {
          "era": 5.4,
          "n": 1,
          "fatigue": "normal"
        },
        "away": {
          "era": 1.23,
          "n": 3,
          "fatigue": "media"
        }
      },
      "formula_version": "v2",
      "graded": true,
      "date": "2026-05-23",
      "game_date": "2026-05-23",
      "park_factor": 0.915,
      "elo_diff": 63.299999999999955,
      "sp_fip_diff": -0.28800000000000026,
      "home_win": 1,
      "total_runs": 2,
      "final": "0-2",
      "ml_result": "win",
      "total_result": "win",
      "backfilled": true
    },
    {
      "game_pk": 824030,
      "matchup": "TEX @ LAA",
      "home": "LAA",
      "away": "TEX",
      "status": "Final",
      "model_p": 0.447,
      "signal": -1.006,
      "adrian_p": 0.297,
      "agree": 4,
      "ml_pick": "TEX",
      "factor_leans": {
        "momentum": -0.4364,
        "pitching": -1.1816,
        "f5": -0.427,
        "bats": -0.7029,
        "schedule": 0.18,
        "manager": 0
      },
      "news_delta": -0.46,
      "base": 8.27,
      "adj_total": 6.868,
      "line": 8.5,
      "side": "under",
      "p_over": 0.287,
      "components": {
        "aStart": -0.8338,
        "hStart": -0.5742,
        "homeContact": -0.078,
        "awayContact": -0.066,
        "aFat": 0.15,
        "hFat": 0
      },
      "streak_home": 1,
      "streak_away": -1,
      "pitcher_recent": {
        "home": {
          "era": 1.59,
          "n": 3,
          "fatigue": "normal"
        },
        "away": {
          "era": 0.41,
          "n": 3,
          "fatigue": "media"
        }
      },
      "formula_version": "v2",
      "graded": true,
      "date": "2026-05-23",
      "game_date": "2026-05-23",
      "park_factor": 0.996,
      "elo_diff": -50.59999999999991,
      "sp_fip_diff": 1.0250000000000004,
      "home_win": 1,
      "total_runs": 7,
      "final": "2-5",
      "ml_result": "loss",
      "total_result": "win",
      "backfilled": true
    },
    {
      "game_pk": 825080,
      "matchup": "COL @ AZ",
      "home": "AZ",
      "away": "COL",
      "status": "Final",
      "model_p": 0.63,
      "signal": 0.5393,
      "adrian_p": 0.78,
      "agree": 5,
      "ml_pick": "AZ",
      "factor_leans": {
        "momentum": 0.6182,
        "pitching": 0.2891,
        "f5": 0.053,
        "bats": 0.6795,
        "schedule": 0.0947,
        "manager": -0.1804
      },
      "news_delta": 0.22,
      "base": 9.97,
      "adj_total": 11.214,
      "line": 10,
      "side": "over",
      "p_over": 0.662,
      "components": {
        "aStart": 1.1,
        "hStart": 0.264,
        "homeContact": -0.036,
        "awayContact": -0.084,
        "aFat": 0,
        "hFat": 0
      },
      "streak_home": -1,
      "streak_away": 1,
      "pitcher_recent": {
        "home": {
          "era": 5.4,
          "n": 3,
          "fatigue": "normal"
        },
        "away": {
          "era": 9.2,
          "n": 3,
          "fatigue": "normal"
        }
      },
      "formula_version": "v2",
      "graded": true,
      "date": "2026-05-23",
      "game_date": "2026-05-23",
      "park_factor": 1.059,
      "elo_diff": 84.09999999999991,
      "sp_fip_diff": -0.04400000000000048,
      "home_win": 1,
      "total_runs": 9,
      "final": "4-5",
      "ml_result": "win",
      "total_result": "loss",
      "backfilled": true
    },
    {
      "game_pk": 823543,
      "matchup": "TB @ NYY",
      "home": "NYY",
      "away": "TB",
      "status": "Postponed",
      "model_p": 0.536,
      "signal": -0.2519,
      "adrian_p": 0.386,
      "agree": 4,
      "ml_pick": "TB",
      "factor_leans": {
        "momentum": -1.0909,
        "pitching": -0.3757,
        "f5": -0.1325,
        "bats": -0.9138,
        "schedule": 0.1956,
        "manager": 0
      },
      "news_delta": 0.23,
      "base": 8.67,
      "adj_total": 8.7994,
      "line": 8.5,
      "side": "over",
      "p_over": 0.541,
      "components": {
        "aStart": -0.011,
        "hStart": 0.0264,
        "homeContact": 0.102,
        "awayContact": 0.012,
        "aFat": 0,
        "hFat": 0
      },
      "streak_home": -3,
      "streak_away": 5,
      "pitcher_recent": {
        "home": {
          "era": 4.32,
          "n": 3,
          "fatigue": "normal"
        },
        "away": {
          "era": 4.15,
          "n": 3,
          "fatigue": "normal"
        }
      },
      "formula_version": "v2",
      "graded": false,
      "date": "2026-05-23",
      "game_date": "2026-09-22",
      "park_factor": 0.992,
      "elo_diff": 10.899999999999864,
      "sp_fip_diff": 0.42700000000000005,
      "backfilled": true
    },
    {
      "game_pk": 824840,
      "matchup": "DET @ BAL",
      "home": "BAL",
      "away": "DET",
      "status": "Postponed",
      "model_p": 0.522,
      "signal": 0.0494,
      "adrian_p": 0.567,
      "agree": 3,
      "ml_pick": "BAL",
      "factor_leans": {
        "momentum": 0.6182,
        "pitching": -1.1893,
        "f5": -0.442,
        "bats": 0.6762,
        "schedule": 0.1422,
        "manager": 0
      },
      "news_delta": 0.15,
      "base": 9.17,
      "adj_total": 9.8696,
      "line": 9,
      "side": "over",
      "p_over": 0.618,
      "components": {
        "aStart": 0.8316,
        "hStart": 0,
        "homeContact": -0.036,
        "awayContact": -0.096,
        "aFat": 0,
        "hFat": 0
      },
      "streak_home": 1,
      "streak_away": -7,
      "pitcher_recent": {
        "home": {
          "era": 4.2,
          "n": 3,
          "fatigue": "normal"
        },
        "away": {
          "era": 7.98,
          "n": 3,
          "fatigue": "normal"
        }
      },
      "formula_version": "v2",
      "graded": false,
      "date": "2026-05-23",
      "game_date": "2026-05-24",
      "park_factor": 1.019,
      "elo_diff": 8.299999999999955,
      "sp_fip_diff": 1.2620000000000005,
      "backfilled": true
    }
  ],
  "backfilled_asof_replay": true
}