{
 "date": "2026-07-08",
 "updated_at": "2026-07-08T23:24:44.565Z",
 "games": {
  "822710": {
   "matchup": "HOU @ WSH",
   "home": "WSH",
   "away": "HOU",
   "espn_id": "401816071",
   "snapshots": [
    {
     "t": "2026-07-08T23:19:43.875Z",
     "state": "in",
     "inn": 2,
     "half": "B",
     "hs": 0,
     "as": 0,
     "wp": 0.604,
     "cons": 0.5404,
     "dis": 0,
     "books": [
      {
       "p": "DraftKings",
       "h": -130,
       "a": 108
      }
     ]
    },
    {
     "t": "2026-07-08T23:24:44.360Z",
     "state": "in",
     "inn": 3,
     "half": "T",
     "hs": 0,
     "as": 0,
     "wp": 0.57,
     "cons": 0.5404,
     "dis": 0,
     "books": [
      {
       "p": "DraftKings",
       "h": -130,
       "a": 108
      }
     ]
    }
   ]
  },
  "822957": {
   "matchup": "NYY @ TB",
   "home": "TB",
   "away": "NYY",
   "espn_id": "401816073",
   "snapshots": [
    {
     "t": "2026-07-08T23:19:43.806Z",
     "state": "in",
     "inn": 3,
     "half": "B",
     "hs": 0,
     "as": 0,
     "wp": 0.588,
     "cons": 0.5248,
     "dis": 0,
     "books": [
      {
       "p": "DraftKings",
       "h": -122,
       "a": 101
      }
     ]
    },
    {
     "t": "2026-07-08T23:24:44.295Z",
     "state": "in",
     "inn": 3,
     "half": "B",
     "hs": 1,
     "as": 0,
     "wp": 0.704,
     "cons": 0.5248,
     "dis": 0,
     "books": [
      {
       "p": "DraftKings",
       "h": -122,
       "a": 101
      }
     ]
    }
   ]
  },
  "823202": {
   "matchup": "TOR @ SF",
   "home": "SF",
   "away": "TOR",
   "espn_id": "401816082",
   "snapshots": [
    {
     "t": "2026-07-08T19:49:11.703Z",
     "state": "in",
     "inn": 1,
     "half": "T",
     "hs": 0,
     "as": 0,
     "wp": 0.464,
     "cons": 0.4687,
     "dis": 0,
     "books": [
      {
       "p": "DraftKings",
       "h": 104,
       "a": -125
      }
     ]
    },
    {
     "t": "2026-07-08T19:54:11.865Z",
     "state": "in",
     "inn": 1,
     "half": "T",
     "hs": 0,
     "as": 0,
     "wp": 0.463,
     "cons": 0.4687,
     "dis": 0,
     "books": [
      {
       "p": "DraftKings",
       "h": 104,
       "a": -125
      }
     ]
    },
    {
     "t": "2026-07-08T19:59:13.553Z",
     "state": "in",
     "inn": 1,
     "half": "T",
     "hs": 0,
     "as": 5,
     "wp": 0.136,
     "cons": 0.4687,
     "dis": 0,
     "books": [
      {
       "p": "DraftKings",
       "h": 104,
       "a": -125
      }
     ]
    },
    {
     "t": "2026-07-08T20:04:13.807Z",
     "state": "in",
     "inn": 1,
     "half": "B",
     "hs": 0,
     "as": 5,
     "wp": 0.138,
     "cons": 0.4687,
     "dis": 0,
     "books": [
      {
       "p": "DraftKings",
       "h": 104,
       "a": -125
      }
     ]
    },
    {
     "t": "2026-07-08T20:09:15.627Z",
     "state": "in",
     "inn": 1,
     "half": "B",
     "hs": 0,
     "as": 5,
     "wp": 0.117,
     "cons": 0.4687,
     "dis": 0,
     "books": [
      {
       "p": "DraftKings",
       "h": 104,
       "a": -125
      }
     ]
    },
    {
     "t": "2026-07-08T20:14:15.857Z",
     "state": "in",
     "inn": 2,
     "half": "T",
     "hs": 0,
     "as": 5,
     "wp": 0.118,
     "cons": 0.4687,
     "dis": 0,
     "books": [
      {
       "p": "DraftKings",
       "h": 104,
       "a": -125
      }
     ]
    },
    {
     "t": "2026-07-08T20:19:17.512Z",
     "state": "in",
     "inn": 2,
     "half": "B",
     "hs": 0,
     "as": 5,
     "wp": 0.118,
     "cons": 0.4687,
     "dis": 0,
     "books": [
      {
       "p": "DraftKings",
       "h": 104,
       "a": -125
      }
     ]
    },
    {
     "t": "2026-07-08T20:24:17.786Z",
     "state": "in",
     "inn": 2,
     "half": "B",
     "hs": 0,
     "as": 5,
     "wp": 0.097,
     "cons": 0.4687,
     "dis": 0,
     "books": [
      {
       "p": "DraftKings",
       "h": 104,
       "a": -125
      }
     ]
    },
    {
     "t": "2026-07-08T20:29:19.514Z",
     "state": "in",
     "inn": 3,
     "half": "B",
     "hs": 0,
     "as": 5,
     "wp": 0.101,
     "cons": 0.4687,
     "dis": 0,
     "books": [
      {
       "p": "DraftKings",
       "h": 104,
       "a": -125
      }
     ]
    },
    {
     "t": "2026-07-08T21:19:55.024Z",
     "state": "in",
     "inn": 6,
     "half": "B",
     "hs": 0,
     "as": 5,
     "wp": 0.04,
     "cons": 0.4687,
     "dis": 0,
     "books": [
      {
       "p": "DraftKings",
       "h": 104,
       "a": -125
      }
     ]
    },
    {
     "t": "2026-07-08T21:24:55.432Z",
     "state": "in",
     "inn": 7,
     "half": "T",
     "hs": 0,
     "as": 5,
     "wp": 0.036,
     "cons": 0.4687,
     "dis": 0,
     "books": [
      {
       "p": "DraftKings",
       "h": 104,
       "a": -125
      }
     ]
    },
    {
     "t": "2026-07-08T21:29:56.975Z",
     "state": "in",
     "inn": 7,
     "half": "B",
     "hs": 0,
     "as": 5,
     "wp": 0.026,
     "cons": 0.4687,
     "dis": 0,
     "books": [
      {
       "p": "DraftKings",
       "h": 104,
       "a": -125
      }
     ]
    },
    {
     "t": "2026-07-08T21:34:57.113Z",
     "state": "in",
     "inn": 7,
     "half": "B",
     "hs": 0,
     "as": 5,
     "wp": 0.023,
     "cons": 0.4687,
     "dis": 0,
     "books": [
      {
       "p": "DraftKings",
       "h": 104,
       "a": -125
      }
     ]
    },
    {
     "t": "2026-07-08T21:39:58.710Z",
     "state": "in",
     "inn": 8,
     "half": "T",
     "hs": 0,
     "as": 5,
     "wp": 0.017,
     "cons": 0.4687,
     "dis": 0,
     "books": [
      {
       "p": "DraftKings",
       "h": 104,
       "a": -125
      }
     ]
    },
    {
     "t": "2026-07-08T21:44:58.942Z",
     "state": "in",
     "inn": 8,
     "half": "T",
     "hs": 0,
     "as": 5,
     "wp": 0.014,
     "cons": 0.4687,
     "dis": 0,
     "books": [
      {
       "p": "DraftKings",
       "h": 104,
       "a": -125
      }
     ]
    },
    {
     "t": "2026-07-08T21:50:00.681Z",
     "state": "in",
     "inn": 8,
     "half": "T",
     "hs": 0,
     "as": 6,
     "wp": 0.007,
     "cons": 0.4687,
     "dis": 0,
     "books": [
      {
       "p": "DraftKings",
       "h": 104,
       "a": -125
      }
     ]
    },
    {
     "t": "2026-07-08T21:55:01.050Z",
     "state": "in",
     "inn": 8,
     "half": "B",
     "hs": 0,
     "as": 7,
     "wp": 0.002,
     "cons": 0.4687,
     "dis": 0,
     "books": [
      {
       "p": "DraftKings",
       "h": 104,
       "a": -125
      }
     ]
    },
    {
     "t": "2026-07-08T22:00:02.547Z",
     "state": "in",
     "inn": 9,
     "half": "T",
     "hs": 0,
     "as": 7,
     "wp": 0.001,
     "cons": 0.4687,
     "dis": 0,
     "books": [
      {
       "p": "DraftKings",
       "h": 104,
       "a": -125
      }
     ]
    }
   ]
  },
  "823360": {
   "matchup": "ATL @ PIT",
   "home": "PIT",
   "away": "ATL",
   "espn_id": "401816069",
   "snapshots": [
    {
     "t": "2026-07-08T23:19:43.773Z",
     "state": "in",
     "inn": 3,
     "half": "T",
     "hs": 0,
     "as": 0,
     "wp": 0.506,
     "cons": 0.527,
     "dis": 0,
     "books": [
      {
       "p": "DraftKings",
       "h": -123,
       "a": 102
      }
     ]
    },
    {
     "t": "2026-07-08T23:24:44.264Z",
     "state": "in",
     "inn": 3,
     "half": "B",
     "hs": 0,
     "as": 0,
     "wp": 0.565,
     "cons": 0.527,
     "dis": 0,
     "books": [
      {
       "p": "DraftKings",
       "h": -123,
       "a": 102
      }
     ]
    }
   ]
  },
  "823605": {
   "matchup": "KC @ NYM",
   "home": "NYM",
   "away": "KC",
   "espn_id": "401816072",
   "snapshots": [
    {
     "t": "2026-07-08T23:19:43.956Z",
     "state": "in",
     "inn": 1,
     "half": "B",
     "hs": 0,
     "as": 0,
     "wp": 0.595,
     "cons": 0.6364,
     "dis": 0,
     "books": [
      {
       "p": "DraftKings",
       "h": -199,
       "a": 163
      }
     ]
    },
    {
     "t": "2026-07-08T23:24:44.415Z",
     "state": "in",
     "inn": 1,
     "half": "B",
     "hs": 1,
     "as": 0,
     "wp": 0.677,
     "cons": 0.6364,
     "dis": 0,
     "books": [
      {
       "p": "DraftKings",
       "h": -199,
       "a": 163
      }
     ]
    }
   ]
  },
  "823848": {
   "matchup": "SEA @ MIA",
   "home": "MIA",
   "away": "SEA",
   "espn_id": "401816075",
   "snapshots": [
    {
     "t": "2026-07-08T23:19:43.849Z",
     "state": "in",
     "inn": 3,
     "half": "T",
     "hs": 1,
     "as": 0,
     "wp": 0.697,
     "cons": 0.4667,
     "dis": 0,
     "books": [
      {
       "p": "DraftKings",
       "h": 105,
       "a": -126
      }
     ]
    },
    {
     "t": "2026-07-08T23:24:44.323Z",
     "state": "in",
     "inn": 3,
     "half": "B",
     "hs": 1,
     "as": 0,
     "wp": 0.774,
     "cons": 0.4667,
     "dis": 0,
     "books": [
      {
       "p": "DraftKings",
       "h": 105,
       "a": -126
      }
     ]
    }
   ]
  },
  "824253": {
   "matchup": "OAK @ DET",
   "home": "DET",
   "away": "OAK",
   "espn_id": "401816068",
   "snapshots": [
    {
     "t": "2026-07-08T23:19:43.720Z",
     "state": "in",
     "inn": 2,
     "half": "B",
     "hs": 1,
     "as": 0,
     "wp": 0.751,
     "cons": 0.5612,
     "dis": 0,
     "books": [
      {
       "p": "DraftKings",
       "h": -142,
       "a": 118
      }
     ]
    },
    {
     "t": "2026-07-08T23:24:44.233Z",
     "state": "in",
     "inn": 2,
     "half": "B",
     "hs": 3,
     "as": 0,
     "wp": 0.876,
     "cons": 0.5612,
     "dis": 0,
     "books": [
      {
       "p": "DraftKings",
       "h": -142,
       "a": 118
      }
     ]
    }
   ]
  },
  "824496": {
   "matchup": "PHI @ CIN",
   "home": "CIN",
   "away": "PHI",
   "espn_id": "401816074",
   "snapshots": [
    {
     "t": "2026-07-08T23:19:43.909Z",
     "state": "in",
     "inn": 1,
     "half": "B",
     "hs": 0,
     "as": 0,
     "wp": 0.632,
     "cons": 0.5638,
     "dis": 0,
     "books": [
      {
       "p": "DraftKings",
       "h": -144,
       "a": 119
      }
     ]
    },
    {
     "t": "2026-07-08T23:24:44.390Z",
     "state": "in",
     "inn": 1,
     "half": "B",
     "hs": 0,
     "as": 0,
     "wp": 0.657,
     "cons": 0.5638,
     "dis": 0,
     "books": [
      {
       "p": "DraftKings",
       "h": -144,
       "a": 119
      }
     ]
    }
   ]
  },
  "824815": {
   "matchup": "CHC @ BAL",
   "home": "BAL",
   "away": "CHC",
   "espn_id": "401816070",
   "snapshots": [
    {
     "t": "2026-07-08T23:19:43.682Z",
     "state": "in",
     "inn": 3,
     "half": "B",
     "hs": 0,
     "as": 1,
     "wp": 0.451,
     "cons": 0.5333,
     "dis": 0,
     "books": [
      {
       "p": "DraftKings",
       "h": -126,
       "a": 105
      }
     ]
    },
    {
     "t": "2026-07-08T23:24:44.204Z",
     "state": "in",
     "inn": 3,
     "half": "B",
     "hs": 0,
     "as": 1,
     "wp": 0.496,
     "cons": 0.5333,
     "dis": 0,
     "books": [
      {
       "p": "DraftKings",
       "h": -126,
       "a": 105
      }
     ]
    }
   ]
  }
 }
}