{"ATL": {"pen_fip": 4.408, "park": 1.013}, "AZ": {"pen_fip": 4.329, "park": 1.059}, "BAL": {"pen_fip": 4.571, "park": 1.019}, "BOS": {"pen_fip": 3.708, "park": 1.112}, "CHC": {"pen_fip": 4.092, "park": 0.963}, "CIN": {"pen_fip": 4.213, "park": 1.088}, "CLE": {"pen_fip": 3.662, "park": 1.036}, "COL": {"pen_fip": 4.805, "park": 1.2}, "CWS": {"pen_fip": 4.439, "park": 0.981}, "DET": {"pen_fip": 4.234, "park": 1.013}, "HOU": {"pen_fip": 3.93, "park": 0.946}, "KC": {"pen_fip": 4.082, "park": 1.06}, "LAA": {"pen_fip": 4.519, "park": 0.996}, "LAD": {"pen_fip": 4.094, "park": 0.935}, "MIA": {"pen_fip": 4.423, "park": 0.948}, "MIL": {"pen_fip": 3.705, "park": 1.0}, "MIN": {"pen_fip": 4.542, "park": 1.02}, "NYM": {"pen_fip": 3.917, "park": 0.891}, "NYY": {"pen_fip": 3.945, "park": 0.992}, "OAK": {"pen_fip": 4.56, "park": 0.916}, "PHI": {"pen_fip": 4.085, "park": 1.017}, "PIT": {"pen_fip": 3.88, "park": 0.998}, "SD": {"pen_fip": 3.753, "park": 0.915}, "SEA": {"pen_fip": 3.967, "park": 0.88}, "SF": {"pen_fip": 4.074, "park": 0.922}, "STL": {"pen_fip": 4.054, "park": 0.93}, "TB": {"pen_fip": 3.881, "park": 0.925}, "TEX": {"pen_fip": 3.841, "park": 1.093}, "TOR": {"pen_fip": 4.08, "park": 1.005}, "WSH": {"pen_fip": 4.837, "park": 1.012}}